legal_utils/__init__.py
legal_utils/data.py
legal_utils/file.py
legal_utils/processing.py
legal_utils/vllm.py
legal_utils-0.2.0.dist-info/METADATA
legal_utils-0.2.0.dist-info/WHEEL
legal_utils-0.2.0.dist-info/top_level.txt
legal_utils-0.2.0.dist-info/RECORD
