Metadata-Version: 2.4
Name: legal-utils
Version: 0.2.0
Summary: Suite d'utilitaires pour le traitement de documents juridiques
Author: Charles Condevaux
Requires-Python: >=3.11
Requires-Dist: numpy
Requires-Dist: pydantic
Requires-Dist: json-repair
Requires-Dist: regex
Requires-Dist: httpx
Requires-Dist: requests
Provides-Extra: test
Requires-Dist: pytest; extra == "test"
